omniCLIP/__init__.py
omniCLIP/data_parsing/CreateGeneAnnotDB.py
omniCLIP/data_parsing/GetCoverageFromBam.py
omniCLIP/data_parsing/LoadReads.py
omniCLIP/data_parsing/ParsingArgs.py
omniCLIP/data_parsing/ParsingPositions.py
omniCLIP/data_parsing/__init__.py
omniCLIP/data_parsing/tools.py
omniCLIP/omniCLIP.py
omniCLIP/omni_stat/FitBinoDirchEmmisionProbabilities.py
omniCLIP/omni_stat/__init__.py
omniCLIP/omni_stat/diag_event_model.py
omniCLIP/omni_stat/emission_prob.py
omniCLIP/omni_stat/mixture_tools.py
omniCLIP/omni_stat/multdirichletVect.py
omniCLIP/omni_stat/sparse_glm.py
omniCLIP/omni_stat/trans.py
omniCLIP/omni_stat/utils.py
omniCLIP/omni_stat/viterbi.c
omniCLIP/omni_stat/viterbi.pyx
omniCLIP/viterbi.cpython-39-darwin.so
omniclip-0.2.8.dist-info/entry_points.txt
omniclip-0.2.8.dist-info/LICENSE
omniclip-0.2.8.dist-info/WHEEL
omniclip-0.2.8.dist-info/METADATA
omniclip-0.2.8.dist-info/RECORD
