Metadata-Version: 2.1
Name: omniclip
Version: 0.2.8
Summary: 
Home-page: https://github.com/y9c/omniCLIP
Author: Philipp Boss
Author-email: philipp.drewe@googlemail.com
Requires-Python: >=3.8,<3.11
Classifier: Programming Language :: Python :: 3
Classifier: Programming Language :: Python :: 3.8
Classifier: Programming Language :: Python :: 3.9
Requires-Dist: Cython (>=0.29.28,<0.30.0)
Requires-Dist: biopython (>=1.79,<2.0)
Requires-Dist: gffutils (>=0.10.1,<0.11.0)
Requires-Dist: h5py (>=3.6.0,<4.0.0)
Requires-Dist: intervaltree (>=3.1.0,<4.0.0)
Requires-Dist: matplotlib (>=3.5.1,<4.0.0)
Requires-Dist: numpy (>=1.22.3,<2.0.0)
Requires-Dist: pandas (>=1.4.2,<2.0.0)
Requires-Dist: pysam (>=0.19.0,<0.20.0)
Requires-Dist: scipy (>=1.8.0,<2.0.0)
Requires-Dist: sklearn (>=0.0,<0.1)
Requires-Dist: statsmodels (>=0.13.2,<0.14.0)
Project-URL: Repository, https://github.com/y9c/omniCLIP
